random_points_on_polygon/__init__.py
random_points_on_polygon/points_generator.py
random_points_on_polygon/samples/__init__.py
random_points_on_polygon/samples/samples.py
tests/__init__.py
tests/test.py
random_points_on_polygon-0.0.3.dist-info/LICENSE
random_points_on_polygon-0.0.3.dist-info/METADATA
random_points_on_polygon-0.0.3.dist-info/WHEEL
random_points_on_polygon-0.0.3.dist-info/top_level.txt
random_points_on_polygon-0.0.3.dist-info/RECORD
