Metadata-Version: 2.1
Name: random-points-on-polygon
Version: 0.0.3
Summary: A simple Python library based on Shapely to generate random points on Polygon or MultiPolygon
Home-page: https://github.com/maurosaladino/random-points-on-polygon
Author: Mauro Saladino
Author-email: maurosaladino7@gmail.com
License: UNKNOWN
Platform: UNKNOWN
Classifier: Programming Language :: Python :: 3
Classifier: License :: OSI Approved :: MIT License
Classifier: Operating System :: OS Independent
Requires-Python: >=3.5
License-File: LICENSE
Requires-Dist: Shapely (==1.8.2)
